[
  {
    "__type__": "cc.SceneAsset",
    "_name": "movimiento",
    "_objFlags": 0,
    "_native": "",
    "scene": {
      "__id__": 1
    },
    "asyncLoadAssets": false
  },
  {
    "__type__": "cc.Scene",
    "_objFlags": 0,
    "_parent": null,
    "_children": [
      {
        "__id__": 2
      }
    ],
    "_active": false,
    "_level": 0,
    "_components": [],
    "_prefab": null,
    "_opacity": 255,
    "_color": {
      "__type__": "cc.Color",
      "r": 255,
      "g": 255,
      "b": 255,
      "a": 255
    },
    "_contentSize": {
      "__type__": "cc.Size",
      "width": 0,
      "height": 0
    },
    "_anchorPoint": {
      "__type__": "cc.Vec2",
      "x": 0,
      "y": 0
    },
    "_scale": {
      "__type__": "cc.Vec3",
      "x": 1,
      "y": 1,
      "z": 1
    },
    "_quat": {
      "__type__": "cc.Quat",
      "x": 0,
      "y": 0,
      "z": 0,
      "w": 1
    },
    "_is3DNode": true,
    "groupIndex": 0,
    "autoReleaseAssets": false,
    "_id": "3ae8816e-4603-4733-b316-15d6c0d897b9"
  },
  {
    "__type__": "cc.Node",
    "_name": "Canvas",
    "_objFlags": 0,
    "_parent": {
      "__id__": 1
    },
    "_children": [
      {
        "__id__": 3
      },
      {
        "__id__": 5
      },
      {
        "__id__": 7
      },
      {
        "__id__": 9
      }
    ],
    "_active": true,
    "_level": 1,
    "_components": [
      {
        "__id__": 11
      },
      {
        "__id__": 12
      }
    ],
    "_prefab": null,
    "_opacity": 255,
    "_color": {
      "__type__": "cc.Color",
      "r": 255,
      "g": 255,
      "b": 255,
      "a": 255
    },
    "_contentSize": {
      "__type__": "cc.Size",
      "width": 960,
      "height": 640
    },
    "_anchorPoint": {
      "__type__": "cc.Vec2",
      "x": 0.5,
      "y": 0.5
    },
    "_position": {
      "__type__": "cc.Vec3",
      "x": 480,
      "y": 320,
      "z": 0
    },
    "_scale": {
      "__type__": "cc.Vec3",
      "x": 1,
      "y": 1.032,
      "z": 1
    },
    "_skewX": 0,
    "_skewY": 0,
    "_is3DNode": false,
    "groupIndex": 0,
    "_id": "2anmWIXaNK0KLBRrENEVD3",
    "_eulerAngles": {
      "__type__": "cc.Vec3",
      "x": 0,
      "y": 0,
      "z": 0
    }
  },
  {
    "__type__": "cc.Node",
    "_name": "Main Camera",
    "_objFlags": 0,
    "_parent": {
      "__id__": 2
    },
    "_children": [],
    "_active": true,
    "_level": 2,
    "_components": [
      {
        "__id__": 4
      }
    ],
    "_prefab": null,
    "_opacity": 255,
    "_color": {
      "__type__": "cc.Color",
      "r": 255,
      "g": 255,
      "b": 255,
      "a": 255
    },
    "_contentSize": {
      "__type__": "cc.Size",
      "width": 0,
      "height": 0
    },
    "_anchorPoint": {
      "__type__": "cc.Vec2",
      "x": 0.5,
      "y": 0.5
    },
    "_position": {
      "__type__": "cc.Vec3",
      "x": -13.433,
      "y": 42.072,
      "z": 554.25626
    },
    "_scale": {
      "__type__": "cc.Vec3",
      "x": 1,
      "y": 1,
      "z": 1
    },
    "_skewX": 0,
    "_skewY": 0,
    "_is3DNode": false,
    "groupIndex": 0,
    "_id": "2bxigLTmhOGrAHsJ677BDW",
    "_eulerAngles": {
      "__type__": "cc.Vec3",
      "x": 0,
      "y": 0,
      "z": 0
    }
  },
  {
    "__type__": "cc.Camera",
    "_name": "",
    "_objFlags": 0,
    "node": {
      "__id__": 3
    },
    "_enabled": true,
    "_cullingMask": 4294967295,
    "_clearFlags": 7,
    "_backgroundColor": {
      "__type__": "cc.Color",
      "r": 0,
      "g": 0,
      "b": 0,
      "a": 255
    },
    "_depth": -1,
    "_zoomRatio": 1,
    "_targetTexture": null,
    "_fov": 60,
    "_orthoSize": 10,
    "_nearClip": 0.1,
    "_farClip": 4096,
    "_ortho": true,
    "_rect": {
      "__type__": "cc.Rect",
      "x": 0,
      "y": 0,
      "width": 1,
      "height": 1
    },
    "_renderStages": 1,
    "_id": "98e5tQ9v9HiaAJwQkwrBUt"
  },
  {
    "__type__": "cc.Node",
    "_name": "score",
    "_objFlags": 0,
    "_parent": {
      "__id__": 2
    },
    "_children": [],
    "_active": true,
    "_level": 2,
    "_components": [
      {
        "__id__": 6
      }
    ],
    "_prefab": null,
    "_opacity": 255,
    "_color": {
      "__type__": "cc.Color",
      "r": 255,
      "g": 255,
      "b": 255,
      "a": 255
    },
    "_contentSize": {
      "__type__": "cc.Size",
      "width": 185.46,
      "height": 50.4
    },
    "_anchorPoint": {
      "__type__": "cc.Vec2",
      "x": 0.5,
      "y": 0.5
    },
    "_position": {
      "__type__": "cc.Vec3",
      "x": -284.444,
      "y": 248.267,
      "z": 0
    },
    "_scale": {
      "__type__": "cc.Vec3",
      "x": 1,
      "y": 1,
      "z": 1
    },
    "_skewX": 0,
    "_skewY": 0,
    "_is3DNode": false,
    "groupIndex": 0,
    "_rotationX": 0,
    "_rotationY": 0,
    "_id": "6dwP37jclBYJQnavv50NTM",
    "_eulerAngles": {
      "__type__": "cc.Vec3",
      "x": 0,
      "y": 0,
      "z": 0
    }
  },
  {
    "__type__": "cc.Label",
    "_name": "",
    "_objFlags": 0,
    "node": {
      "__id__": 5
    },
    "_enabled": true,
    "_materials": [],
    "_useOriginalSize": false,
    "_string": "Score: 0",
    "_N$string": "Score: 0",
    "_fontSize": 49.8,
    "_lineHeight": 40,
    "_enableWrapText": true,
    "_N$file": null,
    "_isSystemFontUsed": true,
    "_spacingX": 0,
    "_batchAsBitmap": false,
    "_N$horizontalAlign": 1,
    "_N$verticalAlign": 1,
    "_N$fontFamily": "Arial",
    "_N$overflow": 0,
    "_N$cacheMode": 0,
    "_id": "6dwyas5RlN15ed2S/ctK/C"
  },
  {
    "__type__": "cc.Node",
    "_name": "Reloj",
    "_objFlags": 0,
    "_parent": {
      "__id__": 2
    },
    "_children": [],
    "_active": true,
    "_level": 2,
    "_components": [
      {
        "__id__": 8
      }
    ],
    "_prefab": null,
    "_opacity": 255,
    "_color": {
      "__type__": "cc.Color",
      "r": 255,
      "g": 255,
      "b": 255,
      "a": 255
    },
    "_contentSize": {
      "__type__": "cc.Size",
      "width": 260.19,
      "height": 50.4
    },
    "_anchorPoint": {
      "__type__": "cc.Vec2",
      "x": 0.5,
      "y": 0.5
    },
    "_position": {
      "__type__": "cc.Vec3",
      "x": 325.108,
      "y": 248.267,
      "z": 0
    },
    "_scale": {
      "__type__": "cc.Vec3",
      "x": 1,
      "y": 1,
      "z": 1
    },
    "_skewX": 0,
    "_skewY": 0,
    "_is3DNode": false,
    "groupIndex": 0,
    "_rotationX": 0,
    "_rotationY": 0,
    "_id": "c7mzoshzhC86q3snHGWLre",
    "_eulerAngles": {
      "__type__": "cc.Vec3",
      "x": 0,
      "y": 0,
      "z": 0
    }
  },
  {
    "__type__": "cc.Label",
    "_name": "",
    "_objFlags": 0,
    "node": {
      "__id__": 7
    },
    "_enabled": true,
    "_materials": [],
    "_useOriginalSize": false,
    "_string": "Hora Actual",
    "_N$string": "Hora Actual",
    "_fontSize": 49.8,
    "_lineHeight": 40,
    "_enableWrapText": true,
    "_N$file": null,
    "_isSystemFontUsed": true,
    "_spacingX": 0,
    "_batchAsBitmap": false,
    "_N$horizontalAlign": 1,
    "_N$verticalAlign": 1,
    "_N$fontFamily": "Arial",
    "_N$overflow": 0,
    "_N$cacheMode": 0,
    "_id": "65rmxY9LpLioIhpJbJkkNk"
  },
  {
    "__type__": "cc.Node",
    "_name": "Nivel",
    "_objFlags": 0,
    "_parent": {
      "__id__": 2
    },
    "_children": [],
    "_active": true,
    "_level": 2,
    "_components": [
      {
        "__id__": 10
      }
    ],
    "_prefab": null,
    "_opacity": 255,
    "_color": {
      "__type__": "cc.Color",
      "r": 255,
      "g": 255,
      "b": 255,
      "a": 255
    },
    "_contentSize": {
      "__type__": "cc.Size",
      "width": 166.06,
      "height": 50.4
    },
    "_anchorPoint": {
      "__type__": "cc.Vec2",
      "x": 0.5,
      "y": 0.5
    },
    "_position": {
      "__type__": "cc.Vec3",
      "x": 12.688,
      "y": 248.267,
      "z": 0
    },
    "_scale": {
      "__type__": "cc.Vec3",
      "x": 1,
      "y": 1,
      "z": 1
    },
    "_skewX": 0,
    "_skewY": 0,
    "_is3DNode": false,
    "groupIndex": 0,
    "_rotationX": 0,
    "_rotationY": 0,
    "_id": "4aJgPREFtJBbrCj6JpB6sj",
    "_eulerAngles": {
      "__type__": "cc.Vec3",
      "x": 0,
      "y": 0,
      "z": 0
    }
  },
  {
    "__type__": "cc.Label",
    "_name": "",
    "_objFlags": 0,
    "node": {
      "__id__": 9
    },
    "_enabled": true,
    "_materials": [],
    "_useOriginalSize": false,
    "_string": "Nivel: 1",
    "_N$string": "Nivel: 1",
    "_fontSize": 49.8,
    "_lineHeight": 40,
    "_enableWrapText": true,
    "_N$file": null,
    "_isSystemFontUsed": true,
    "_spacingX": 0,
    "_batchAsBitmap": false,
    "_N$horizontalAlign": 1,
    "_N$verticalAlign": 1,
    "_N$fontFamily": "Arial",
    "_N$overflow": 0,
    "_N$cacheMode": 0,
    "_id": "83f+68+4ZNCr5mhn1R7BRo"
  },
  {
    "__type__": "cc.Canvas",
    "_name": "",
    "_objFlags": 0,
    "node": {
      "__id__": 2
    },
    "_enabled": true,
    "_designResolution": {
      "__type__": "cc.Size",
      "width": 960,
      "height": 640
    },
    "_fitWidth": false,
    "_fitHeight": true,
    "_id": "14H7/Hi/FNR5x4/KfaE6s9"
  },
  {
    "__type__": "dd482A07mBJtJnMGucbRbpc",
    "_name": "",
    "_objFlags": 0,
    "node": {
      "__id__": 2
    },
    "_enabled": true,
    "circlePrefab": {
      "__uuid__": "e212f115-7333-4cdc-8956-4003d98ec40d"
    },
    "cursorPrefab": {
      "__uuid__": "b7e265f9-5ebf-47e9-a52b-2094cbf48420"
    },
    "touchPointPrefab": {
      "__uuid__": "66f3879c-e84a-41b8-b2e2-ed84421e9c8f"
    },
    "presioneAquiPrefab": {
      "__uuid__": "9402057b-4c48-4409-a5ad-09843a3b85fc"
    },
    "flechaApuntaArribaPrefab": {
      "__uuid__": "e9604868-5570-4062-904c-ee11292c3bc0"
    },
    "flechaApuntaAbajoPrefab": {
      "__uuid__": "85682277-a4ba-498d-aa9c-d5c83a4d887f"
    },
    "touchPointNotificacionPrefab": {
      "__uuid__": "626c2766-f113-4cec-b13f-4c12f400c659"
    },
    "scoreDisplay": {
      "__id__": 6
    },
    "nivelDisplay": {
      "__id__": 10
    },
    "horaDisplay": {
      "__id__": 8
    },
    "notificacionComida": {
      "__uuid__": "85ee7d06-37a8-4a81-8069-37372698098e"
    },
    "notificacionTiempo": {
      "__uuid__": "ca5b5217-7cf6-4e4f-8f79-ff8a802aa59d"
    },
    "levelSound": {
      "__uuid__": "14fe617a-08c2-46aa-82b0-07f5cf5f6523"
    },
    "positionCircle": {
      "__type__": "cc.Vec2",
      "x": 0,
      "y": 0
    },
    "positionNotification": {
      "__type__": "cc.Vec2",
      "x": 0,
      "y": 0
    },
    "positionTouchpoint": {
      "__type__": "cc.Vec2",
      "x": 0,
      "y": -88
    },
    "cantVeces": 2,
    "aux": 1,
    "contador": 0,
    "horaNotificacion": 12,
    "minutoNotificacion": 50,
    "horaInicial": 0,
    "minutoInicial": 0,
    "velocidadReloj": 1,
    "tiempoMax": 60,
    "cantVecesPresiona": 0,
    "arregloSecuencia": [],
    "arregloSecuenciaCorrecta": [],
    "arregloSecuenciaUsuario": [],
    "secuenciafinal": [],
    "nivel": 1,
    "controlFlecha": 0,
    "_id": "a2/91M+F1LGL4zj53B3yyH"
  }
]